{
  "cards": [
	{"name": "Allo Piano 2.1", "dsp_options":["Subwoofer mode","Lowpass","Dual Mode"]},
	{"name": "Allo Katana", "dsp_options":["DSP Program","Deemphasis","DoP"]},
	{"name": "PianoDACPlus", "dsp_options":["Subwoofer mode","Lowpass","Dual Mode"]},
	{"name": "Hifiberry DAC Plus", "dsp_options":["DSP Program","Clock Missing Period"]},
	{"name": "JustBoom DAC Boards", "dsp_options":["DSP Program","Clock Missing Period"]},
	{"name": "JustBoom Digi Boards", "dsp_options":["Tx Source"]},
	{"name": "HDMI Out", "dsp_options":["hdmi audio format Function"]},
	{"name": "TauDAC - DM101", "dsp_options":["Anti-Clipping Mode","Dither","Filter"]},
	{"name": "Volumio ESS 9028QM", "dsp_options":["FIR Filter Type","IIR Filter Select"]},
	{"name": "Analog RCA Output", "dsp_options":["FIR Filter Type","IIR Filter Select"]}
  ]
}
